{
  "country": "Germany",
  "last_updated": "2026-04-15T23:35:46.081506+00:00",
  "story_count": 91,
  "stories": [
    {
      "title": "New EU entry-exit system causing up to three-hour delays, say airports",
      "source": "The Guardian",
      "url": "https://www.theguardian.com/world/2026/apr/15/eu-entry-exit-system-ees-delays-airports-border-checks",
      "published_date": "2026-04-15T15:46:53+00:00",
      "category": "Diplomacy"
    },
    {
      "title": "South Africa appoints veteran Afrikaner politician Roelf Meyer as US ambassador amid tense Trump ties",
      "source": "Deutsche Welle",
      "url": "https://www.dw.com/en/south-africa-appoints-veteran-afrikaner-politician-roelf-meyer-as-us-ambassador-amid-tense-trump-ties/a-76794872?maca=en-rss-en-all-1573-rdf",
      "published_date": "2026-04-15T15:18:00+00:00",
      "category": "Diplomacy"
    },
    {
      "title": "Does Viktor Orbán’s defeat signal a wider backlash against ‘the forces of darkness’?",
      "source": "The Guardian",
      "url": "https://www.theguardian.com/world/2026/apr/15/this-is-europe-end-of-orban-impact-on-european-elections",
      "published_date": "2026-04-15T14:18:23+00:00",
      "category": "Diplomacy"
    },
    {
      "title": "EU chief urges bloc-wide push on age verification app to protect children online",
      "source": "Deutsche Welle",
      "url": "https://www.dw.com/en/eu-chief-urges-bloc-wide-push-on-age-verification-app-to-protect-children-online/a-76788202?maca=en-rss-en-all-1573-rdf",
      "published_date": "2026-04-15T13:22:00+00:00",
      "category": "Diplomacy"
    },
    {
      "title": "Hungary’s voters shunned Orbán – but it may be too early to celebrate end of Europe’s far right",
      "source": "The Guardian",
      "url": "https://www.theguardian.com/world/2026/apr/15/hungary-election-voters-orban-europe-far-right-peter-magyar",
      "published_date": "2026-04-15T12:46:29+00:00",
      "category": "Diplomacy"
    },
    {
      "title": "Antisemitismus: Deutschland ist laut EU-Bericht zu streng mit Antisemitismus-Begriff",
      "source": "ZEIT Online",
      "url": "https://www.zeit.de/gesellschaft/zeitgeschehen/2026-04/antisemitismus-deutschland-ihra-israel-europarat-kritik",
      "published_date": "2026-04-15T10:41:06+00:00",
      "category": "Diplomacy"
    },
    {
      "title": "Today in Germany: A roundup of the latest news on Wednesday",
      "source": "The Local Germany",
      "url": "https://www.thelocal.de/20260415/today-in-germany-a-roundup-of-the-latest-news-on-wednesday-116",
      "published_date": "2026-04-15T06:28:01+00:00",
      "category": "Diplomacy"
    },
    {
      "title": "Ukraine war briefing: Orbán’s defeat in Hungary could unlock €90bn loan for Ukraine, says EU official",
      "source": "The Guardian",
      "url": "https://www.theguardian.com/world/2026/apr/15/ukraine-war-briefing-orbans-defeat-in-hungary-could-unlock-90bn-loan-for-ukraine-says-eu-official",
      "published_date": "2026-04-15T02:04:39+00:00",
      "category": "Diplomacy"
    },
    {
      "title": "Is the EU back in vogue? – podcast",
      "source": "The Guardian",
      "url": "https://www.theguardian.com/news/audio/2026/apr/15/is-the-eu-back-in-vogue-podcast",
      "published_date": "2026-04-15T02:00:55+00:00",
      "category": "Diplomacy"
    },
    {
      "title": "In a joyful Budapest, I see the chance of an unprecedented transition | Timothy Garton Ash",
      "source": "The Guardian",
      "url": "https://www.theguardian.com/commentisfree/2026/apr/14/budapest-populists-donald-trump-viktor-orban-hungary-europe",
      "published_date": "2026-04-14T16:43:24+00:00",
      "category": "Diplomacy"
    },
    {
      "title": "Israeli ambassador to Germany condemns Bezalel Smotrich’s tirade against chancellor",
      "source": "The Guardian",
      "url": "https://www.theguardian.com/world/2026/apr/14/israeli-ambassador-germany-condemns-bezalel-smotrich-chancellor-friedrich-merz-nazi-regime",
      "published_date": "2026-04-14T15:45:08+00:00",
      "category": "Diplomacy"
    },
    {
      "title": "Q&A: Who will get Germany's tax-free bonus?",
      "source": "The Local Germany",
      "url": "https://www.thelocal.de/20260414/qa-who-will-get-germanys-tax-free-bonus",
      "published_date": "2026-04-14T15:01:50+00:00",
      "category": "Diplomacy"
    },
    {
      "title": "Magyar set to make rare appearance on Hungary’s state media after accusing them of spreading Orbán propaganda – Europe live",
      "source": "The Guardian",
      "url": "https://www.theguardian.com/world/live/2026/apr/14/hungary-peter-magyar-viktor-orban-eu-ukraine-russia-europe-live-news-updates",
      "published_date": "2026-04-14T11:45:02+00:00",
      "category": "Diplomacy"
    },
    {
      "title": "Deutsch-ukrainische Regierungskonsultationen: Merz und Selenskyj verkünden \"strategische Partnerschaft\"",
      "source": "ZEIT Online",
      "url": "https://www.zeit.de/politik/ausland/2026-04/friedrich-merz-wolodymyr-selenskyj-regierungskonsultationen-berlin-ukraine-hilfe-eu",
      "published_date": "2026-04-14T11:38:06+00:00",
      "category": "Diplomacy"
    },
    {
      "title": "Germany, Ukraine discuss drone deal as Merz hosts Zelenskyy",
      "source": "Deutsche Welle",
      "url": "https://www.dw.com/en/germany-ukraine-discuss-drone-deal-as-merz-hosts-zelenskyy/live-76770415?maca=en-rss-en-ger-1023-rdf",
      "published_date": "2026-04-14T11:31:00+00:00",
      "category": "Diplomacy"
    },
    {
      "title": "Germany, Ukraine discuss drone deal as Merz hosts Zelenskyy",
      "source": "Deutsche Welle",
      "url": "https://www.dw.com/en/germany-ukraine-discuss-drone-deal-as-merz-hosts-zelenskyy/live-76770415?maca=en-rss-en-all-1573-rdf",
      "published_date": "2026-04-14T11:31:00+00:00",
      "category": "Diplomacy"
    },
    {
      "title": "Spanish premier calls for a stronger bond between China and EU on Beijing trip",
      "source": "Deutsche Welle",
      "url": "https://www.dw.com/en/spanish-premier-calls-for-a-stronger-bond-between-china-and-eu-on-beijing-trip/a-76770392?maca=en-rss-en-all-1573-rdf",
      "published_date": "2026-04-14T09:59:00+00:00",
      "category": "Diplomacy"
    },
    {
      "title": "Ukraine's Zelensky to meet German Chancellor Merz in Berlin",
      "source": "The Local Germany",
      "url": "https://www.thelocal.de/20260414/ukraines-zelensky-to-meet-german-chancellor-merz-in-berlin",
      "published_date": "2026-04-14T09:04:23+00:00",
      "category": "Diplomacy"
    },
    {
      "title": "How the European job market will change with new pay transparency rules",
      "source": "The Local Germany",
      "url": "https://www.thelocal.de/20260414/how-the-european-job-market-will-change-with-new-pay-transparency-rules",
      "published_date": "2026-04-14T08:37:53+00:00",
      "category": "Diplomacy"
    },
    {
      "title": "Viktor Orbán inspired rightwingers across the EU and in Britain. His defeat could represent a turning of the tide | Polly Toynbee",
      "source": "The Guardian",
      "url": "https://www.theguardian.com/commentisfree/2026/apr/14/viktor-orban-europe-britain-hard-right-populism",
      "published_date": "2026-04-14T05:00:00+00:00",
      "category": "Diplomacy"
    },
    {
      "title": "France seeks release of 86-year-old French widow detained by ICE",
      "source": "The Guardian",
      "url": "https://www.theguardian.com/us-news/2026/apr/15/french-widow-detained-ice-marie-therese-ross",
      "published_date": "2026-04-15T21:42:39+00:00",
      "category": "Military"
    },
    {
      "title": "Can Trump get a better Iran deal than Obama?",
      "source": "Deutsche Welle",
      "url": "https://www.dw.com/en/can-trump-get-a-better-iran-deal-than-obama/a-76798388?maca=en-rss-en-all-1573-rdf",
      "published_date": "2026-04-15T18:48:00+00:00",
      "category": "Military"
    },
    {
      "title": "Germany, the UK warn the Iran war distracts from Ukraine and oil price rises help Russia",
      "source": "Deutsche Welle",
      "url": "https://www.dw.com/en/germany-the-uk-warn-the-iran-war-distracts-from-ukraine-and-oil-price-rises-help-russia/a-76797004?maca=en-rss-en-ger-1023-rdf",
      "published_date": "2026-04-15T17:22:00+00:00",
      "category": "Military"
    },
    {
      "title": "Germany, the UK warn the Iran war distracts from Ukraine and oil price rises help Russia",
      "source": "Deutsche Welle",
      "url": "https://www.dw.com/en/germany-the-uk-warn-the-iran-war-distracts-from-ukraine-and-oil-price-rises-help-russia/a-76797004?maca=en-rss-en-all-1573-rdf",
      "published_date": "2026-04-15T17:22:00+00:00",
      "category": "Military"
    },
    {
      "title": "Germany, the UK warn the Iran war distracts from Ukraine and oil price rises help Russia",
      "source": "Deutsche Welle",
      "url": "https://www.dw.com/en/germany-the-uk-warn-the-iran-war-distracts-from-ukraine-and-oil-price-rises-help-russia/a-76797004?maca=en-rss-en-eu-2092-rdf",
      "published_date": "2026-04-15T17:22:00+00:00",
      "category": "Military"
    },
    {
      "title": "Peace activist, 91, walks across Ireland in protest against US military stopovers",
      "source": "The Guardian",
      "url": "https://www.theguardian.com/world/2026/apr/15/peace-activist-lelia-doolan-walk-ireland-protest-us-military-shannon-airport",
      "published_date": "2026-04-15T16:04:48+00:00",
      "category": "Military"
    },
    {
      "title": "Berlin hosts Sudan Conference: a brutal, forgotten conflict",
      "source": "Deutsche Welle",
      "url": "https://www.dw.com/en/berlin-hosts-sudan-conference-a-brutal-forgotten-conflict/a-76798246?maca=en-rss-en-ger-1023-rdf",
      "published_date": "2026-04-15T16:02:00+00:00",
      "category": "Military"
    },
    {
      "title": "Berlin hosts Sudan Conference: a brutal, forgotten conflict",
      "source": "Deutsche Welle",
      "url": "https://www.dw.com/en/berlin-hosts-sudan-conference-a-brutal-forgotten-conflict/a-76798246?maca=en-rss-en-all-1573-rdf",
      "published_date": "2026-04-15T16:02:00+00:00",
      "category": "Military"
    },
    {
      "title": "Germany: Sudan aid conference in Berlin raises €1.3B",
      "source": "Deutsche Welle",
      "url": "https://www.dw.com/en/germany-sudan-aid-conference-in-berlin-raises-€1-3b/a-76786563?maca=en-rss-en-ger-1023-rdf",
      "published_date": "2026-04-15T15:26:00+00:00",
      "category": "Military"
    },
    {
      "title": "Germany: Sudan aid conference in Berlin raises €1.3B",
      "source": "Deutsche Welle",
      "url": "https://www.dw.com/en/germany-sudan-aid-conference-in-berlin-raises-€1-3b/a-76786563?maca=en-rss-en-all-1573-rdf",
      "published_date": "2026-04-15T15:26:00+00:00",
      "category": "Military"
    },
    {
      "title": "What's behind Israel's attacks along Lebanon's Litani River?",
      "source": "Deutsche Welle",
      "url": "https://www.dw.com/en/what-s-behind-israel-s-attacks-along-lebanon-s-litani-river/a-76783514?maca=en-rss-en-all-1573-rdf",
      "published_date": "2026-04-15T14:12:00+00:00",
      "category": "Military"
    },
    {
      "title": "Iran: Hundreds of thousands of jobs lost due to war",
      "source": "Deutsche Welle",
      "url": "https://www.dw.com/en/iran-hundreds-of-thousands-of-jobs-lost-due-to-war/a-76794860?maca=en-rss-en-all-1573-rdf",
      "published_date": "2026-04-15T14:07:00+00:00",
      "category": "Military"
    },
    {
      "title": "Defense in Orbit: Germany Goes Big in the Military Space Race",
      "source": "Der Spiegel",
      "url": "https://www.spiegel.de/international/germany/defense-in-orbit-germany-goes-big-in-the-military-space-race-a-0b1f15e2-740e-4c8b-b759-52d8a49fab31#ref=rss",
      "published_date": "2026-04-15T14:00:00+00:00",
      "category": "Military"
    },
    {
      "title": "India's aviation boom hits turbulence amid Iran war",
      "source": "Deutsche Welle",
      "url": "https://www.dw.com/en/india-s-aviation-boom-hits-turbulence-amid-iran-war/a-76790258?maca=en-rss-en-all-1573-rdf",
      "published_date": "2026-04-15T12:52:00+00:00",
      "category": "Military"
    },
    {
      "title": "Iran war: White House mulling fresh talks with Tehran",
      "source": "Deutsche Welle",
      "url": "https://www.dw.com/en/iran-war-white-house-mulling-fresh-talks-with-tehran/live-76783967?maca=en-rss-en-all-1573-rdf",
      "published_date": "2026-04-15T12:32:00+00:00",
      "category": "Military"
    },
    {
      "title": "Germany: Berlin conference for Sudan aims to raise over $1B",
      "source": "Deutsche Welle",
      "url": "https://www.dw.com/en/germany-berlin-conference-for-sudan-aims-to-raise-over-1b/a-76786563?maca=en-rss-en-ger-1023-rdf",
      "published_date": "2026-04-15T11:22:00+00:00",
      "category": "Military"
    },
    {
      "title": "Germany: Berlin conference for Sudan aims to raise over $1B",
      "source": "Deutsche Welle",
      "url": "https://www.dw.com/en/germany-berlin-conference-for-sudan-aims-to-raise-over-1b/a-76786563?maca=en-rss-en-all-1573-rdf",
      "published_date": "2026-04-15T11:22:00+00:00",
      "category": "Military"
    },
    {
      "title": "Xi hails China-Russia ties, signals bigger role in Iran war",
      "source": "Deutsche Welle",
      "url": "https://www.dw.com/en/xi-hails-china-russia-ties-signals-bigger-role-in-iran-war/a-76787130?maca=en-rss-en-all-1573-rdf",
      "published_date": "2026-04-15T10:13:00+00:00",
      "category": "Military"
    },
    {
      "title": "Hidden treasures: Spanish archaeologists discover trove of ancient shipwrecks in Bay of Gibraltar",
      "source": "The Guardian",
      "url": "https://www.theguardian.com/science/2026/apr/15/hidden-treasures-spanish-archaeologists-discover-trove-of-ancient-shipwrecks-in-bay-of-gibraltar",
      "published_date": "2026-04-15T08:00:03+00:00",
      "category": "Military"
    },
    {
      "title": "Nuba Mountains: a fragile refuge on Sudan's frontline",
      "source": "Deutsche Welle",
      "url": "https://www.dw.com/en/nuba-mountains-a-fragile-refuge-on-sudan-s-frontline/a-76766294?maca=en-rss-en-all-1573-rdf",
      "published_date": "2026-04-15T06:47:00+00:00",
      "category": "Military"
    },
    {
      "title": "Firefighters battle huge blaze at Australian oil refinery",
      "source": "Deutsche Welle",
      "url": "https://www.dw.com/en/firefighters-battle-huge-blaze-at-australian-oil-refinery/a-76801562?maca=en-rss-en-all-1573-rdf",
      "published_date": "2026-04-15T22:41:00+00:00",
      "category": "Energy"
    },
    {
      "title": "Solar power in Morocco's desert: Bold vision, mixed results",
      "source": "Deutsche Welle",
      "url": "https://www.dw.com/en/solar-power-in-morocco-s-desert-bold-vision-mixed-results/a-75387618?maca=en-rss-en-all-1573-rdf",
      "published_date": "2026-04-15T11:56:00+00:00",
      "category": "Energy"
    },
    {
      "title": "US: Maine pushes for first statewide pause on AI data centers",
      "source": "Deutsche Welle",
      "url": "https://www.dw.com/en/us-maine-pushes-for-first-statewide-pause-on-ai-data-centers/a-76784015?maca=en-rss-en-all-1573-rdf",
      "published_date": "2026-04-15T03:58:00+00:00",
      "category": "Energy"
    },
    {
      "title": "Why India walked away from its bid to host COP33",
      "source": "Deutsche Welle",
      "url": "https://www.dw.com/en/why-india-walked-away-from-its-bid-to-host-cop33/a-76778682?maca=en-rss-en-all-1573-rdf",
      "published_date": "2026-04-14T13:34:00+00:00",
      "category": "Energy"
    },
    {
      "title": "Dieselgate: Audi bosses, engineers set for long trial as plea deal fails",
      "source": "Deutsche Welle",
      "url": "https://www.dw.com/en/dieselgate-audi-bosses-engineers-set-for-long-trial-as-plea-deal-fails/a-76768350?maca=en-rss-en-ger-1023-rdf",
      "published_date": "2026-04-13T17:51:00+00:00",
      "category": "Energy"
    },
    {
      "title": "Dieselgate: Audi bosses, engineers set for long trial as plea deal fails",
      "source": "Deutsche Welle",
      "url": "https://www.dw.com/en/dieselgate-audi-bosses-engineers-set-for-long-trial-as-plea-deal-fails/a-76768350?maca=en-rss-en-all-1573-rdf",
      "published_date": "2026-04-13T17:51:00+00:00",
      "category": "Energy"
    },
    {
      "title": "India news: Delhi looks to ban fossil fuel two-wheelers from 2028",
      "source": "Deutsche Welle",
      "url": "https://www.dw.com/en/india-news-delhi-looks-to-ban-fossil-fuel-two-wheelers-from-2028/live-76745829?maca=en-rss-en-all-1573-rdf",
      "published_date": "2026-04-11T07:53:00+00:00",
      "category": "Energy"
    },
    {
      "title": "Starmer says he is ‘fed up’ with Trump and Putin’s impact on UK energy costs",
      "source": "The Guardian",
      "url": "https://www.theguardian.com/politics/2026/apr/10/starmer-fed-up-trump-uk-politics",
      "published_date": "2026-04-10T07:55:53+00:00",
      "category": "Energy"
    },
    {
      "title": "A new German-Polish project shows how cities can be heated without fossil fuels",
      "source": "The Local Germany",
      "url": "https://www.thelocal.de/20260409/a-new-german-polish-project-shows-how-cities-can-be-heated-without-fossil-fuels",
      "published_date": "2026-04-09T14:40:18+00:00",
      "category": "Energy"
    },
    {
      "title": "Strait of Hormuz not open, Abu Dhabi’s oil chief says as crude prices rise",
      "source": "The Guardian",
      "url": "https://www.theguardian.com/business/2026/apr/09/oil-price-rises-as-markets-question-durability-of-middle-east-ceasefire-iran",
      "published_date": "2026-04-09T14:14:06+00:00",
      "category": "Energy"
    },
    {
      "title": "‘The danger and value of water are in my blood’: how rain fences are making Dutch homes more climate resilient",
      "source": "The Guardian",
      "url": "https://www.theguardian.com/environment/2026/apr/09/rain-fences-dutch-homes-climate-resilient",
      "published_date": "2026-04-09T13:00:50+00:00",
      "category": "Energy"
    },
    {
      "title": "German health minister announces billions in cutbacks",
      "source": "Deutsche Welle",
      "url": "https://www.dw.com/en/german-health-minister-announces-billions-in-cutbacks/a-76796338?maca=en-rss-en-ger-1023-rdf",
      "published_date": "2026-04-15T15:02:00+00:00",
      "category": "Economy"
    },
    {
      "title": "German health minister announces billions in cutbacks",
      "source": "Deutsche Welle",
      "url": "https://www.dw.com/en/german-health-minister-announces-billions-in-cutbacks/a-76796338?maca=en-rss-en-all-1573-rdf",
      "published_date": "2026-04-15T15:02:00+00:00",
      "category": "Economy"
    },
    {
      "title": "How was Orbán defeated? With energetic campaigning and cunning exploitation of his weaknesses | Tibor Dessewffy",
      "source": "The Guardian",
      "url": "https://www.theguardian.com/commentisfree/2026/apr/15/viktor-orban-defeated-energetic-campaigning-peter-magyar-hungary-election",
      "published_date": "2026-04-15T14:06:58+00:00",
      "category": "Economy"
    },
    {
      "title": "German word of the day: Blitzer",
      "source": "The Local Germany",
      "url": "https://www.thelocal.de/20260415/german-word-of-the-day-blitzer",
      "published_date": "2026-04-15T13:24:09+00:00",
      "category": "Economy"
    },
    {
      "title": "Higher co-pays, fewer services: The cuts coming for Germany's public health insurance",
      "source": "The Local Germany",
      "url": "https://www.thelocal.de/20260415/higher-co-pays-fewer-services-the-cuts-coming-for-germanys-public-health-insurance",
      "published_date": "2026-04-15T11:30:04+00:00",
      "category": "Economy"
    },
    {
      "title": "Women's workwear: When proper fit becomes a safety issue",
      "source": "Deutsche Welle",
      "url": "https://www.dw.com/en/women-s-workwear-when-proper-fit-becomes-a-safety-issue/a-76777532?maca=en-rss-en-ger-1023-rdf",
      "published_date": "2026-04-15T10:01:00+00:00",
      "category": "Economy"
    },
    {
      "title": "Women's workwear: When proper fit becomes a safety issue",
      "source": "Deutsche Welle",
      "url": "https://www.dw.com/en/women-s-workwear-when-proper-fit-becomes-a-safety-issue/a-76777532?maca=en-rss-en-all-1573-rdf",
      "published_date": "2026-04-15T10:01:00+00:00",
      "category": "Economy"
    },
    {
      "title": "Tax Day is a reminder of America’s unequal tax system. But we can fix it | Zohran Mamdani, Gabriel Zucman and Joseph Stiglitz",
      "source": "The Guardian",
      "url": "https://www.theguardian.com/commentisfree/2026/apr/15/tax-day-united-states-unequal-taxation",
      "published_date": "2026-04-15T10:00:26+00:00",
      "category": "Economy"
    },
    {
      "title": "Aegon offloads 200-year-old UK business to Standard Life for £2bn",
      "source": "The Guardian",
      "url": "https://www.theguardian.com/business/2026/apr/15/aegon-offloads-200-year-old-uk-business-to-standard-life",
      "published_date": "2026-04-15T09:23:24+00:00",
      "category": "Economy"
    },
    {
      "title": "France's Renault slashes engineer jobs amid pressure from Chinese carmakers",
      "source": "Deutsche Welle",
      "url": "https://www.dw.com/en/france-s-renault-slashes-engineer-jobs-amid-pressure-from-chinese-carmakers/a-76783924?maca=en-rss-en-all-1573-rdf",
      "published_date": "2026-04-15T00:30:00+00:00",
      "category": "Economy"
    },
    {
      "title": "France's Renault slashes engineer jobs amid pressure from Chinese carmakers",
      "source": "Deutsche Welle",
      "url": "https://www.dw.com/en/france-s-renault-slashes-engineer-jobs-amid-pressure-from-chinese-carmakers/a-76783924?maca=en-rss-en-eu-2092-rdf",
      "published_date": "2026-04-15T00:30:00+00:00",
      "category": "Economy"
    },
    {
      "title": "Lufthansa pilots to strike again for 2 more days, leading to a full working week of disruption",
      "source": "Deutsche Welle",
      "url": "https://www.dw.com/en/lufthansa-pilots-to-strike-again-for-2-more-days-leading-to-a-full-working-week-of-disruption/a-76783319?maca=en-rss-en-ger-1023-rdf",
      "published_date": "2026-04-14T19:06:00+00:00",
      "category": "Economy"
    },
    {
      "title": "Lufthansa pilots to strike again for 2 more days, leading to a full working week of disruption",
      "source": "Deutsche Welle",
      "url": "https://www.dw.com/en/lufthansa-pilots-to-strike-again-for-2-more-days-leading-to-a-full-working-week-of-disruption/a-76783319?maca=en-rss-en-all-1573-rdf",
      "published_date": "2026-04-14T19:06:00+00:00",
      "category": "Economy"
    },
    {
      "title": "UK woman fears being stranded in Spain over new Home Office border rules",
      "source": "The Guardian",
      "url": "https://www.theguardian.com/uk-news/2026/apr/14/uk-woman-fears-being-stranded-spain-new-home-office-border-rules",
      "published_date": "2026-04-14T17:33:34+00:00",
      "category": "Economy"
    },
    {
      "title": "Reeves arrives at IMF with little leeway to prove its UK downgrade wrong",
      "source": "The Guardian",
      "url": "https://www.theguardian.com/business/2026/apr/14/rachel-reeves-arrives-at-imf-with-little-leeway-to-prove-its-uk-downgrade-wrong",
      "published_date": "2026-04-14T17:27:57+00:00",
      "category": "Economy"
    },
    {
      "title": "UK steel exports to EU at risk as bloc doubles tariffs and halves quotas",
      "source": "The Guardian",
      "url": "https://www.theguardian.com/business/2026/apr/14/uk-steel-exports-eu-risk-tariffs-quotas",
      "published_date": "2026-04-14T13:53:35+00:00",
      "category": "Economy"
    },
    {
      "title": "Spanish prime minister’s wife charged with corruption",
      "source": "The Guardian",
      "url": "https://www.theguardian.com/world/2026/apr/14/spanish-prime-minister-wife-charged-with-corruption-pedro-sanchez-begona-gomez",
      "published_date": "2026-04-14T10:58:37+00:00",
      "category": "Economy"
    },
    {
      "title": "Wirtschaftskrise: Deutsche Autohersteller starten mit Verkaufsminus ins Jahr 2026",
      "source": "ZEIT Online",
      "url": "https://www.zeit.de/wirtschaft/2026-04/autoindustrie-absatz-bmw-volkswagen-mercedes-china",
      "published_date": "2026-04-14T10:42:21+00:00",
      "category": "Economy"
    },
    {
      "title": "Today in Germany: A roundup of the latest news on Tuesday",
      "source": "The Local Germany",
      "url": "https://www.thelocal.de/20260414/today-in-germany-a-roundup-of-the-latest-news-on-tuesday-119",
      "published_date": "2026-04-14T06:39:01+00:00",
      "category": "Economy"
    },
    {
      "title": "Benin's finance minister wins presidential election with 94%",
      "source": "Deutsche Welle",
      "url": "https://www.dw.com/en/benin-s-finance-minister-wins-presidential-election-with-94/a-76769500?maca=en-rss-en-all-1573-rdf",
      "published_date": "2026-04-14T02:29:00+00:00",
      "category": "Economy"
    },
    {
      "title": "Schwarzfahren: SPD fordert von Union Entkriminalisierung des Fahrens ohne Fahrschein",
      "source": "ZEIT Online",
      "url": "https://www.zeit.de/politik/deutschland/2026-04/schwarzfahren-spd-cdu-csu-entkriminalisierung-strafrecht",
      "published_date": "2026-04-15T23:20:35+00:00",
      "category": "Local Events"
    },
    {
      "title": "Tennis: Tennis-Duo Siegemund und Lys in Stuttgart chancenlos",
      "source": "ZEIT Online",
      "url": "https://www.zeit.de/news/2026-04/15/tennis-talent-noha-akugue-scheidet-in-stuttgart-aus",
      "published_date": "2026-04-15T21:01:56+00:00",
      "category": "Local Events"
    },
    {
      "title": "Eishockey-Playoffs: Köln gleicht nach Verlängerungs-Krimi gegen Berlin aus",
      "source": "ZEIT Online",
      "url": "https://www.zeit.de/news/2026-04/15/koeln-gleicht-nach-verlaengerungs-krimi-gegen-berlin-aus",
      "published_date": "2026-04-15T20:57:35+00:00",
      "category": "Local Events"
    },
    {
      "title": "Hungary’s prime minister-elect vows to suspend ‘propaganda machine’ state media",
      "source": "The Guardian",
      "url": "https://www.theguardian.com/world/2026/apr/15/hungary-prime-minister-elect-peter-magyar-suspend-state-media-propaganda",
      "published_date": "2026-04-15T13:32:30+00:00",
      "category": "Local Events"
    },
    {
      "title": "Attacks on US academics: A microcosm of a larger threat to democracy",
      "source": "Deutsche Welle",
      "url": "https://www.dw.com/en/attacks-on-us-academics-a-microcosm-of-a-larger-threat-to-democracy/a-76777273?maca=en-rss-en-all-1573-rdf",
      "published_date": "2026-04-15T13:08:00+00:00",
      "category": "Local Events"
    },
    {
      "title": "Turkey: School shooting leaves 9 dead",
      "source": "Deutsche Welle",
      "url": "https://www.dw.com/en/turkey-school-shooting-leaves-9-dead/a-76791529?maca=en-rss-en-all-1573-rdf",
      "published_date": "2026-04-15T12:43:00+00:00",
      "category": "Local Events"
    },
    {
      "title": "Magyar ‘is going to do good job’, Trump says as he distances himself from Orbán – Europe live",
      "source": "The Guardian",
      "url": "https://www.theguardian.com/world/live/2026/apr/15/peter-magyar-hungary-president-media-viktor-orban-european-union-europe-latest",
      "published_date": "2026-04-15T11:29:24+00:00",
      "category": "Local Events"
    },
    {
      "title": "Viktor Orbán und die AfD: Das schmerzt auch die AfD",
      "source": "ZEIT Online",
      "url": "https://www.zeit.de/politik/deutschland/2026-04/viktor-orban-afd-ungarn-verbuendete-niederlage-reaktion",
      "published_date": "2026-04-15T11:25:09+00:00",
      "category": "Local Events"
    },
    {
      "title": "The Brexit delusion is dead – so now Keir Starmer doesn’t need to pretend any more | Rafael Behr",
      "source": "The Guardian",
      "url": "https://www.theguardian.com/commentisfree/2026/apr/15/brexit-delusion-keir-starmer-europe-prime-minister",
      "published_date": "2026-04-15T09:00:03+00:00",
      "category": "Local Events"
    },
    {
      "title": "Germany: Man found guilty in Pelicot-style rape case",
      "source": "Deutsche Welle",
      "url": "https://www.dw.com/en/germany-man-found-guilty-in-pelicot-style-rape-case/a-76775746?maca=en-rss-en-ger-1023-rdf",
      "published_date": "2026-04-15T08:37:00+00:00",
      "category": "Local Events"
    },
    {
      "title": "Germany: Man found guilty in Pelicot-style rape case",
      "source": "Deutsche Welle",
      "url": "https://www.dw.com/en/germany-man-found-guilty-in-pelicot-style-rape-case/a-76775746?maca=en-rss-en-all-1573-rdf",
      "published_date": "2026-04-15T08:37:00+00:00",
      "category": "Local Events"
    },
    {
      "title": "Where passengers in Saxony are affected by public transport strikes this week",
      "source": "The Local Germany",
      "url": "https://www.thelocal.de/20260415/where-passengers-in-saxony-are-affected-by-public-transport-strikes-this-week",
      "published_date": "2026-04-15T08:26:04+00:00",
      "category": "Local Events"
    },
    {
      "title": "Hungary: What's next for Peter Magyar after election win?",
      "source": "Deutsche Welle",
      "url": "https://www.dw.com/en/hungary-what-s-next-for-peter-magyar-after-election-win/a-76785927?maca=en-rss-en-all-1573-rdf",
      "published_date": "2026-04-15T08:24:00+00:00",
      "category": "Local Events"
    },
    {
      "title": "Hungary: What's next for Peter Magyar after election win?",
      "source": "Deutsche Welle",
      "url": "https://www.dw.com/en/hungary-what-s-next-for-peter-magyar-after-election-win/a-76785927?maca=en-rss-en-eu-2092-rdf",
      "published_date": "2026-04-15T08:24:00+00:00",
      "category": "Local Events"
    },
    {
      "title": "'BerlinPay': How a new tourism initiative aims to clean up Germany's capital city",
      "source": "The Local Germany",
      "url": "https://www.thelocal.de/20260415/berlinpay-how-a-new-tourism-initiative-aims-to-clean-up-germanys-capital-city",
      "published_date": "2026-04-15T08:08:40+00:00",
      "category": "Local Events"
    },
    {
      "title": "Germany news: Lufthansa air crew strike after pilot walkout",
      "source": "Deutsche Welle",
      "url": "https://www.dw.com/en/germany-news-lufthansa-air-crew-strike-after-pilot-walkout/live-76785451?maca=en-rss-en-ger-1023-rdf",
      "published_date": "2026-04-15T07:55:00+00:00",
      "category": "Local Events"
    },
    {
      "title": "Germany news: Lufthansa air crew strike after pilot walkout",
      "source": "Deutsche Welle",
      "url": "https://www.dw.com/en/germany-news-lufthansa-air-crew-strike-after-pilot-walkout/live-76785451?maca=en-rss-en-all-1573-rdf",
      "published_date": "2026-04-15T07:55:00+00:00",
      "category": "Local Events"
    },
    {
      "title": "Lufthansa pilots' union calls for second new strike this week",
      "source": "The Local Germany",
      "url": "https://www.thelocal.de/20260415/lufthansa-pilots-union-calls-for-second-new-strike-this-week",
      "published_date": "2026-04-15T07:05:03+00:00",
      "category": "Local Events"
    },
    {
      "title": "Turkey school shooting injures 16, teenage attacker dead",
      "source": "Deutsche Welle",
      "url": "https://www.dw.com/en/turkey-school-shooting-injures-16-teenage-attacker-dead/a-76784713?maca=en-rss-en-all-1573-rdf",
      "published_date": "2026-04-15T06:18:00+00:00",
      "category": "Local Events"
    },
    {
      "title": "Hungary beware: authoritarianism can be checked, but it is rarely dismissed with a single blow | Blanche Leridon",
      "source": "The Guardian",
      "url": "https://www.theguardian.com/commentisfree/2026/apr/15/hungary-authoritarianism-poland-rule-of-law",
      "published_date": "2026-04-15T04:00:58+00:00",
      "category": "Local Events"
    }
  ]
}